pyclearsky/__init__.py
pyclearsky/clearskyrad.py
pyclearsky/pytest_helpers.py
pyclearsky-0.3.6.dist-info/METADATA
pyclearsky-0.3.6.dist-info/WHEEL
pyclearsky-0.3.6.dist-info/licenses/AUTHORS.rst
pyclearsky-0.3.6.dist-info/licenses/LICENSE
pyclearsky-0.3.6.dist-info/RECORD
