Metadata-Version: 2.4
Name: pyclearsky
Version: 0.3.6
Summary: implements the equations from Ashrae Fundamentals 2009 for clear sky in Python
Project-URL: Homepage, https://github.com/santoshphilip/pyclearsky
Project-URL: Repository, https://github.com/santoshphilip/pyclearsky
Project-URL: Issues, https://github.com/santoshphilip/pyclearsky/issues
Author-email: Santosh Philip <santosh_philip@nomail.com>
License: MPL 2.0
License-File: AUTHORS.rst
License-File: LICENSE
Keywords: ashrae,clear-sky,pyclearsky,solar
Classifier: Development Status :: 5 - Production/Stable
Classifier: Intended Audience :: Developers
Classifier: License :: OSI Approved :: Mozilla Public License 2.0 (MPL 2.0)
Classifier: Natural Language :: English
Requires-Python: <4.0,>=3.9
